pyxend/__init__.py
pyxend/cli.py
pyxend/license_gen.py
pyxend/parser.py
pyxend/templates/.vscodeignore
pyxend/templates/extension.js.j2
pyxend/templates/main.py
pyxend/templates/package.json.j2
pyxend-0.3.1.dist-info/licenses/LICENSE
pyxend-0.3.1.dist-info/METADATA
pyxend-0.3.1.dist-info/WHEEL
pyxend-0.3.1.dist-info/entry_points.txt
pyxend-0.3.1.dist-info/top_level.txt
pyxend-0.3.1.dist-info/RECORD
