Metadata-Version: 2.4
Name: pyxend
Version: 0.3.1
Summary: Python framework for building VS Code extensions
Author-email: codeflane <nta16022013@gmail.com>
License-Expression: MIT
Requires-Python: >=3.8
License-File: LICENSE
Requires-Dist: click
Requires-Dist: jinja2
Dynamic: license-file
Dynamic: requires-python
